{
	"componentPath": "./src/wwObjectRow.vue",
	"content": {
		"type": "ww-row",
		"data": {
			"wwObjects": [],
			"align": "center",
			"justify": "center"
		}
	},
	"upsales": {
		"wwAnalytics": {
			"click": false
		}
	},
	"cmsOptions": {
		"wwObjectHover": {
			"pluses": false,
			"hoverClass": "ww-columns-hover"
		},
		"wwObjectMenu": {
			"items": [
				{
					"if": "wwLayout",
					"name": "ADD_BEFORE",
					"text": {
						"en": "Before",
						"fr": "Avant"
					},
					"icon": "wwi wwi-add",
					"action": "wwLayout:addBefore"
				},
				{
					"if": "wwLayout",
					"name": "ADD_AFTER",
					"text": {
						"en": "After",
						"fr": "Après"
					},
					"icon": "wwi wwi-add",
					"action": "wwLayout:addAfter"
				},

				{
					"name": "OPTIONS",
					"main": true,
					"text": {
						"en": "Options",
						"fr": "Options"
					},
					"icon": "wwi wwi-edit-other",
					"action": "edit"
				}
			]
		}
	}
}
